turbobus/__init__.py
turbobus/bus.py
turbobus/decorators.py
turbobus/exception.py
turbobus-1.0.0a0.dist-info/METADATA
turbobus-1.0.0a0.dist-info/WHEEL
turbobus-1.0.0a0.dist-info/RECORD
