Metadata-Version: 2.1
Name: turbobus
Version: 1.0.0a0
Summary: TurboBus is an opinionated implementation of Command Responsibility Segregation pattern in python
License: MIT
Author: Christopher A. Flores
Author-email: christopher.flores@codexitos.com
Requires-Python: >=3.11,<4.0
Classifier: License :: OSI Approved :: MIT License
Classifier: Programming Language :: Python :: 3
Classifier: Programming Language :: Python :: 3.11
